Strands-0.1.0.dist-info/RECORD
Strands-0.1.0.dist-info/LICENSE
Strands-0.1.0.dist-info/WHEEL
Strands-0.1.0.dist-info/top_level.txt
Strands-0.1.0.dist-info/METADATA
strands/__init__.py
strands/strands.cpython-39-darwin.so
