Metadata-Version: 2.1
Name: Strands
Version: 0.1.0
Summary: "Strands - Standing waves approximations for the n-dimensional Schrödinger problem (with n = 2)."
Home-page: https://github.com/twist-numerical/strands
Author: Toon Baeyens
Author-email: toon.baeyens@ugent.be
License: MIT
Project-URL: Source, https://github.com/twist-numerical/strands
Keywords: schrodinger equation,eigenvalues,numerical methods
Platform: any
Requires-Python: >=3.6
License-File: LICENSE
Requires-Dist: numpy
